{"timestamp": "2026-04-01T17:09:15.693746+00:00", "question": "Najdi smlouvy kde je objednatelem Muzeum Mladobolestavska, p\u0159\u00edsp\u011bvkov\u00e1 organizace", "answer": "Smlouvy, kde je objednatelem Muzeum Mladobolestavska, p\u0159\u00edsp\u011bvkov\u00e1 organizace, jsou uvedeny v poskytnut\u00e9m kontextu:\n\n1. Smlouva o d\u00edlo \u010d. S-0042/00353639/2024\n   - Objednatel: Muzeum Mladobolestavska, p\u0159\u00edsp\u011bvkov\u00e1 organizace\n   - Zhotovitel: Hlav\u00e1\u010dek- architekti, s.r.o.\n   - P\u0159edm\u011bt: nen\u00ed p\u0159esn\u011b uveden v \u00faryvku, ale je to smlouva o d\u00edlo\n\n2. Smlouva o d\u00edlo \u010d. 41/00353639/2024\n   - Objednatel: Muzeum Mladobolestavska, p\u0159\u00edsp\u011bvkov\u00e1 organizace\n   - Dodavatel: Projektov\u00fd ateli\u00e9r pro architekturu a pozemn\u00ed stavby spol. s r.o.\n   - P\u0159edm\u011bt: Obnova hospod\u00e1\u0159sk\u00e9 budovy v are\u00e1lu fary v Doln\u00ed Krup\u00e9 \u2014 zpracov\u00e1n\u00ed projektov\u00e9 dokumentace (PD)\n\nTyto smlouvy jsou uzav\u0159eny mezi Muzeem Mladobolestavska, p\u0159\u00edsp\u011bvkovou organizac\u00ed jako objednatelem, a uveden\u00fdmi dodavateli.", "sources": [{"source": "S-0041-00353639-2024a.pdf", "page": 1}]}
{"timestamp": "2026-04-01T17:17:28.810621+00:00", "question": "Kto jsou smluvni strany u prodeje kameroveho systemu mereni geometrie podvozku?", "answer": "Smluvn\u00ed strany u prodeje kamerov\u00e9ho syst\u00e9mu m\u011b\u0159en\u00ed geometrie podvozku jsou:\n\n- Kupuj\u00edc\u00ed: St\u0159edn\u00ed odborn\u00e9 u\u010dili\u0161t\u011b, Nov\u00e9 Stra\u0161ec\u00ed, Sportovn\u00ed 1135, zastoupen\u00e9 Ing. Bc. Janem Nechutn\u00fdm\n- Prod\u00e1vaj\u00edc\u00ed: AD TECHNIK, s.r.o., se s\u00eddlem Moskevsk\u00e1 1569/65b, 101 00 Praha 10 - Vr\u0161ovice, zastoupen\u00e1 p. Janem Svobodou, jednatelem spole\u010dnosti", "sources": [{"source": "Kupn\u00ed smlouva dev\u00edtim\u00edstn\u00fd automobil.pdf", "page": 5}]}
{"timestamp": "2026-04-01T21:26:55.924504+00:00", "question": "Kto jsou smluvni strany u prodeje kameroveho systemu mereni geometrie podvozku?", "answer": "Smluvn\u00ed strany u prodeje kamerov\u00e9ho syst\u00e9mu m\u011b\u0159en\u00ed geometrie podvozku jsou:\n\n- Kupuj\u00edc\u00ed: St\u0159edn\u00ed odborn\u00e9 u\u010dili\u0161t\u011b, Nov\u00e9 Stra\u0161ec\u00ed, Sportovn\u00ed 1135, zastoupen\u00e9 Ing. Bc. Janem Nechutn\u00fdm\n- Prod\u00e1vaj\u00edc\u00ed: AD TECHNIK, s.r.o., se s\u00eddlem Moskevsk\u00e1 1569/65b, 101 00 Praha 10 - Vr\u0161ovice, zastoupena p. Janem Svobodou, jednatelem spole\u010dnosti", "sources": [{"source": "Kupn\u00ed smlouva dev\u00edtim\u00edstn\u00fd automobil.pdf", "page": 5}]}
